README.md
setup.cfg
setup.py
PyProfane/__init__.py
PyProfane/constants.py
PyProfane/functions.py
PyProfane/main.py
PyProfane.egg-info/PKG-INFO
PyProfane.egg-info/SOURCES.txt
PyProfane.egg-info/dependency_links.txt
PyProfane.egg-info/top_level.txt
PyProfane/data/comments.txt
PyProfane/data/swearWords.txt
tests/__init__.py
tests/function_test.py