Metadata-Version: 2.1
Name: PyProfane
Version: 1.0.7
Summary: A library to censor and detect offensive words in strings.
Home-page: https://github.com/ieshaan12/PyProfane
Author: Ieshaan Saxena
Author-email: ieshaan1999@gmail.com
License: MIT
Download-URL: https://github.com/ieshaan12/PyProfane/archive/v1.0.7.tar.gz
Platform: UNKNOWN
Classifier: Development Status :: 4 - Beta
Classifier: Natural Language :: English
Classifier: Programming Language :: Python :: 3
Classifier: License :: OSI Approved :: MIT License
Classifier: Operating System :: OS Independent
